pyjacker/__init__.py
pyjacker/ase.py
pyjacker/breakpoints.py
pyjacker/cna.py
pyjacker/genes.py
pyjacker/html_reports.py
pyjacker/outlier_expression.py
pyjacker/pyjacker.py
pyjacker-1.1.5.dist-info/LICENSE
pyjacker-1.1.5.dist-info/METADATA
pyjacker-1.1.5.dist-info/WHEEL
pyjacker-1.1.5.dist-info/entry_points.txt
pyjacker-1.1.5.dist-info/top_level.txt
pyjacker-1.1.5.dist-info/RECORD
