Metadata-Version: 2.1
Name: pyjacker
Version: 1.1.5
Summary: Enhancer hijacking detection from WGS and RNAseq.
Author-email: Etienne Sollier <etienne.sollier@dkfz.de>
Project-URL: Homepage, https://github.com/CompEpigen/pyjacker
Classifier: Programming Language :: Python :: 3
Classifier: License :: OSI Approved :: MIT License
Classifier: Operating System :: OS Independent
Requires-Python: >=3.7
License-File: LICENSE
Requires-Dist: numpy >=1.10.0
Requires-Dist: pandas >=1.3.0
Requires-Dist: vcfpy >=0.13.5
Requires-Dist: scipy >=1.7.3
Requires-Dist: statsmodels >=0.13.5
Requires-Dist: pyyaml >=6.0
Requires-Dist: matplotlib >=3.4.3
Requires-Dist: tqdm >=4.66.0
Requires-Dist: figeno >=1.6.4
